<PAMDataset>
  <Metadata domain="Esri">
    <MDI key="PyramidResamplingType">NEAREST</MDI>
  </Metadata>
  <PAMRasterBand band="1">
    <Histograms>
      <HistItem>
        <HistMin>596.9500122070313</HistMin>
        <HistMax>604.9927978515625</HistMax>
        <BucketCount>256</BucketCount>
        <IncludeOutOfRange>1</IncludeOutOfRange>
        <Approximate>0</Approximate>
        <HistCounts>9|1|3|5|5|8|19|24|39|40|43|52|72|88|88|100|110|109|98|100|128|125|131|140|117|145|144|130|122|149|121|112|110|107|110|109|111|137|137|131|136|139|108|133|116|110|134|133|112|127|130|141|156|155|139|144|143|136|159|168|147|155|128|127|147|127|130|146|152|166|158|182|160|172|165|180|190|164|169|189|192|191|190|208|192|188|206|218|204|203|231|238|286|248|271|297|271|253|249|246|232|247|223|272|247|230|221|234|215|212|221|245|223|232|226|221|231|208|240|209|229|228|238|206|238|221|215|240|227|209|234|227|229|212|225|221|234|236|217|211|235|223|232|216|225|231|223|235|237|230|280|316|339|377|413|451|460|494|547|559|574|596|630|616|650|674|687|658|699|718|718|724|744|772|771|754|773|803|785|802|809|796|756|791|764|775|818|828|878|866|893|942|905|954|923|953|964|915|938|913|905|864|884|855|829|808|783|818|784|750|775|759|729|707|734|717|663|695|656|660|649|617|649|647|643|613|617|594|556|560|522|528|506|471|465|437|432|392|383|358|326|315|282|271|248|220|204|175|159|132|112|90|65|41|17|1</HistCounts>
      </HistItem>
      <HistItem>
        <HistMin>0</HistMin>
        <HistMax>-1</HistMax>
        <BucketCount>1</BucketCount>
        <IncludeOutOfRange>1</IncludeOutOfRange>
        <Approximate>0</Approximate>
        <HistCounts>0</HistCounts>
      </HistItem>
    </Histograms>
    <Metadata>
      <MDI key="STATISTICS_COVARIANCES">3.145788815981824</MDI>
      <MDI key="STATISTICS_EXCLUDEDVALUES"></MDI>
      <MDI key="STATISTICS_MAXIMUM">604.99279785156</MDI>
      <MDI key="STATISTICS_MEAN">602.20991663035</MDI>
      <MDI key="STATISTICS_MINIMUM">596.95001220703</MDI>
      <MDI key="STATISTICS_SKIPFACTORX">1</MDI>
      <MDI key="STATISTICS_SKIPFACTORY">1</MDI>
      <MDI key="STATISTICS_STDDEV">1.7736371714592</MDI>
    </Metadata>
  </PAMRasterBand>
</PAMDataset>
